color/__init__.py
color/__main__.py
color/color.py
color/get.py
monkey_color-0.1.5.post2.dist-info/METADATA
monkey_color-0.1.5.post2.dist-info/WHEEL
monkey_color-0.1.5.post2.dist-info/top_level.txt
monkey_color-0.1.5.post2.dist-info/RECORD
