Metadata-Version: 2.1
Name: monkey-color
Version: 0.1.5.post2
Summary: 有色文字
Home-page: https://github.com/a3510377/color
Author: monkey
Author-email: a102009102009@gmail.com
License: UNKNOWN
Platform: UNKNOWN
